aqualink_sdk/__init__.py
aqualink_sdk/api_client.py
aqualink_sdk/configuration.py
aqualink_sdk/exceptions.py
aqualink_sdk/model_utils.py
aqualink_sdk/rest.py
aqualink_sdk/api/__init__.py
aqualink_sdk/api/aggregate_api.py
aqualink_sdk/api/collections_api.py
aqualink_sdk/api/data_uploads_api.py
aqualink_sdk/api/google_cloud_storage_api.py
aqualink_sdk/api/health_check_api.py
aqualink_sdk/api/regions_api.py
aqualink_sdk/api/sensors_api.py
aqualink_sdk/api/site_applications_api.py
aqualink_sdk/api/site_points_of_interest_api.py
aqualink_sdk/api/sites_api.py
aqualink_sdk/api/surveys_api.py
aqualink_sdk/api/time_series_api.py
aqualink_sdk/api/users_api.py
aqualink_sdk/apis/__init__.py
aqualink_sdk/model/__init__.py
aqualink_sdk/model/collection.py
aqualink_sdk/model/collection_data_dto.py
aqualink_sdk/model/coordinates.py
aqualink_sdk/model/create_collection_dto.py
aqualink_sdk/model/create_region_dto.py
aqualink_sdk/model/create_region_dto_polygon.py
aqualink_sdk/model/create_site_application_dto.py
aqualink_sdk/model/create_site_dto.py
aqualink_sdk/model/create_site_survey_point_dto.py
aqualink_sdk/model/create_survey_dto.py
aqualink_sdk/model/create_survey_media_dto.py
aqualink_sdk/model/create_user_dto.py
aqualink_sdk/model/daily_data.py
aqualink_sdk/model/data_uploads.py
aqualink_sdk/model/data_uploads_delete_dto.py
aqualink_sdk/model/deploy_spotter_dto.py
aqualink_sdk/model/edit_survey_dto.py
aqualink_sdk/model/edit_survey_media_dto.py
aqualink_sdk/model/exclude_spotter_dates_dto.py
aqualink_sdk/model/exclusion_dates.py
aqualink_sdk/model/historical_monthly_mean.py
aqualink_sdk/model/inline_object.py
aqualink_sdk/model/inline_object1.py
aqualink_sdk/model/inline_response200.py
aqualink_sdk/model/inline_response2001.py
aqualink_sdk/model/inline_response2001_metlog.py
aqualink_sdk/model/inline_response2001_metlog_wind_gust_speed.py
aqualink_sdk/model/inline_response2001_sofar_wave_model.py
aqualink_sdk/model/inline_response2001_sofar_wave_model_wind_gust_speed.py
aqualink_api-1.0.8.dist-info/METADATA
aqualink_api-1.0.8.dist-info/WHEEL
aqualink_api-1.0.8.dist-info/top_level.txt
aqualink_api-1.0.8.dist-info/RECORD
