Metadata-Version: 2.1
Name: aqualink-api
Version: 1.0.8
Summary: Aqualink API documentation
Home-page: https://pypi.org/project/aqualink-api/
Author: OpenAPI Generator community
Author-email: team@openapitools.org
License: UNKNOWN
Keywords: OpenAPI,OpenAPI-Generator,Aqualink API documentation
Platform: UNKNOWN
Requires-Python: >=3.6
Requires-Dist: urllib3 (>=1.25.3)
Requires-Dist: python-dateutil
